guided_molecule_gen/__init__.py
guided_molecule_gen/bionemo_model_metadata.py
guided_molecule_gen/inference_client.py
guided_molecule_gen/inference_client_service_test.py
guided_molecule_gen/inference_client_triton_test.py
guided_molecule_gen/optimizer.py
guided_molecule_gen/optimizer_integration_test.py
guided_molecule_gen/optimizer_unit_test.py
guided_molecule_gen/oracles.py
guided_molecule_gen/oracles_test.py
guided_molecule_gen/testutils/__init__.py
guided_molecule_gen/testutils/check_client.py
bionemo_controlled_generation-0.3.0.dist-info/LICENSE.txt
bionemo_controlled_generation-0.3.0.dist-info/METADATA
bionemo_controlled_generation-0.3.0.dist-info/WHEEL
bionemo_controlled_generation-0.3.0.dist-info/top_level.txt
bionemo_controlled_generation-0.3.0.dist-info/RECORD
