Metadata-Version: 2.1
Name: bionemo-controlled-generation
Version: 0.3.0
Summary: Guided molecule generation via the BioNemo cloud service
Author-email: NVIDIA Bionemo <bionemofeedback@nvidia.com>
Maintainer-email: Kevin Boyd <kboyd@nvidia.com>
License: NVIDIA Software Evaluation License Agreement
Project-URL: Homepage, https://www.nvidia.com/en-us/clara/bionemo/
Project-URL: Documentation, https://developer.nvidia.com/docs/bionemo-service/index.html
Keywords: bionemo
Classifier: Development Status :: 4 - Beta
Classifier: Programming Language :: Python :: 3
Classifier: Programming Language :: Python :: 3.8
Classifier: Programming Language :: Python :: 3.9
Classifier: Programming Language :: Python :: 3.10
Classifier: Programming Language :: Python :: 3.11
Classifier: Programming Language :: Python :: 3.12
License-File: LICENSE.txt
Requires-Dist: bionemo >=0.3
Requires-Dist: cma
Requires-Dist: numpy
Requires-Dist: rdkit
Requires-Dist: tritonclient[http]
Provides-Extra: devtools
Requires-Dist: black ==23.7.0 ; extra == 'devtools'
Requires-Dist: coverage[toml] ; extra == 'devtools'
Requires-Dist: isort ==5.12.0 ; extra == 'devtools'
Requires-Dist: pytest ; extra == 'devtools'
Provides-Extra: extra_oracles
Requires-Dist: networkx ; extra == 'extra_oracles'
Requires-Dist: numpy ==1.22.4 ; extra == 'extra_oracles'
Requires-Dist: pytdc ; extra == 'extra_oracles'
Requires-Dist: scikit-learn ==0.22.1 ; extra == 'extra_oracles'
